nisse/__init__.py
nisse/data_iterator.py
nisse/version.py
tests/__init__.py
tests/test_sanity.py
Nisse-0.0.1.20190501114803.dist-info/LICENSE.md
Nisse-0.0.1.20190501114803.dist-info/METADATA
Nisse-0.0.1.20190501114803.dist-info/WHEEL
Nisse-0.0.1.20190501114803.dist-info/entry_points.txt
Nisse-0.0.1.20190501114803.dist-info/top_level.txt
Nisse-0.0.1.20190501114803.dist-info/RECORD
