Metadata-Version: 2.1
Name: Nisse
Version: 0.0.1.20190501114803
Summary: A package for easing return of multiple values
Home-page: https://github.com/cnheider/nisse
Author: Christian Heider Nielsen
Author-email: cnheider@yandex.com
Maintainer: Christian Heider Nielsen
Maintainer-email: cnheider@yandex.com
License: Apache License, Version 2.0
Download-URL: https://github.com/cnheider/nisse/releases
Keywords: python reinforcement-learning interface api
Platform: UNKNOWN
Classifier: Development Status :: 4 - Beta
Classifier: Environment :: Console
Classifier: Intended Audience :: End Users/Desktop
Classifier: Intended Audience :: Developers
Classifier: License :: OSI Approved :: Apache Software License
Classifier: Operating System :: MacOS :: MacOS X
Classifier: Operating System :: Microsoft :: Windows
Classifier: Operating System :: POSIX
Classifier: Operating System :: OS Independent
Classifier: Programming Language :: Python :: 3
Classifier: Natural Language :: English
Requires-Python: >=3
Requires-Dist: numpy
Requires-Dist: six
Requires-Dist: pytest
Provides-Extra: all
